latex_functions/__init__.py
latex_functions/latex_functions.py
latex_functions-0.0.1.dist-info/METADATA
latex_functions-0.0.1.dist-info/WHEEL
latex_functions-0.0.1.dist-info/top_level.txt
latex_functions-0.0.1.dist-info/RECORD
